odoo/addons/l10n_be_eco_tax/README.rst
odoo/addons/l10n_be_eco_tax/__init__.py
odoo/addons/l10n_be_eco_tax/__manifest__.py
odoo/addons/l10n_be_eco_tax/hooks.py
odoo/addons/l10n_be_eco_tax/data/account_account_template_data.xml
odoo/addons/l10n_be_eco_tax/data/account_tax_code_template.xml
odoo/addons/l10n_be_eco_tax/data/account_tax_template_bebat_data.xml
odoo/addons/l10n_be_eco_tax/data/account_tax_template_recupel_in_data.xml
odoo/addons/l10n_be_eco_tax/data/account_tax_template_recupel_out_data.xml
odoo/addons/l10n_be_eco_tax/i18n/l10n_be_eco_tax.pot
odoo/addons/l10n_be_eco_tax/readme/CONFIGURE.rst
odoo/addons/l10n_be_eco_tax/readme/CONTRIBUTORS.rst
odoo/addons/l10n_be_eco_tax/readme/DESCRIPTION.rst
odoo/addons/l10n_be_eco_tax/readme/INSTALL.rst
odoo/addons/l10n_be_eco_tax/readme/USAGE.rst
odoo/addons/l10n_be_eco_tax/static/description/icon.png
odoo/addons/l10n_be_eco_tax/static/description/index.html
odoo_addon_l10n_be_eco_tax-16.0.1.0.1.2.dist-info/METADATA
odoo_addon_l10n_be_eco_tax-16.0.1.0.1.2.dist-info/WHEEL
odoo_addon_l10n_be_eco_tax-16.0.1.0.1.2.dist-info/top_level.txt
odoo_addon_l10n_be_eco_tax-16.0.1.0.1.2.dist-info/RECORD
